MANIFEST.in
README.txt
setup.py
SMPy.egg-info/PKG-INFO
SMPy.egg-info/SOURCES.txt
SMPy.egg-info/dependency_links.txt
SMPy.egg-info/requires.txt
SMPy.egg-info/top_level.txt
docs/_build/html/_sources/blocks.txt
docs/_build/html/_sources/constraints.txt
docs/_build/html/_sources/index.txt
docs/_build/html/_sources/jsonValidator.txt
docs/_build/html/_sources/options.txt
docs/_build/html/_sources/questions.txt
docs/_build/html/_sources/surveys.txt
evaluation/__init__.py
evaluation/correlation.py
evaluation/evaluation.py
evaluation/loadHITs.py
evaluation/make_survey.py
evaluation/objects.py
evaluation/phonology.py
evaluation/simulation.py
surveyman/__init__.py
surveyman/jsonValidator.py
surveyman/examples/BackwardsBranching.py
surveyman/examples/BranchToSubblock.py
surveyman/examples/SimpleSurvey.py
surveyman/examples/TwoBranchesOneBlock.py
surveyman/examples/TwoBranchesOneBlock2.py
surveyman/examples/TwoBranchesOneSubblock2.py
surveyman/examples/__init__.py
surveyman/examples/example_survey.py
surveyman/examples/subblock_example.py
surveyman/survey/__ids__.py
surveyman/survey/__init__.py
surveyman/survey/blocks.py
surveyman/survey/constraints.py
surveyman/survey/options.py
surveyman/survey/questions.py
surveyman/survey/survey_exceptions.py
surveyman/survey/surveys.py
surveyman/test/BlockTests.py
surveyman/test/ConstraintTests.py
surveyman/test/SurveyTests.py
surveyman/test/__init__.py
surveyman/test/__main__.py