Metadata-Version: 1.0
Name: SMPy
Version: 1.0.3
Summary: Python front-end to the SurveyMan Language and Runtime
Home-page: http://surveyman.github.io/SMPy
Author: Emma Tosch
Author-email: etosch@cs.umass.edu
License: CRAPL
Platform: UNKNOWN
